LICENSE
MANIFEST.in
NOTICE
README.rst
THANKS
UNLICENSE
setup.py
docs/Makefile
docs/api.rst
docs/conf.py
docs/index.rst
docs/make.bat
docs/news.rst
docs/poll.rst
docs/uzmq.rst
docs/zmq.rst
examples/echo.py
examples/echo_client.py
examples/echo_zmq.py
examples/echo_zmq_client.py
examples/publisher.py
examples/subscriber.py
tests/test_poll.py
tests/test_zmq.py
uzmq/__init__.py
uzmq/poll.py
uzmq/sock.py
uzmq/util.py
uzmq.egg-info/PKG-INFO
uzmq.egg-info/SOURCES.txt
uzmq.egg-info/dependency_links.txt
uzmq.egg-info/requires.txt
uzmq.egg-info/top_level.txt